modelgraph/__init__.py
modelgraph/__main__.py
modelgraph/cli.py
modelgraph/dependency_graph.py
modelgraph/gui.py
modelgraph-1.0.1.dist-info/LICENSE
modelgraph-1.0.1.dist-info/METADATA
modelgraph-1.0.1.dist-info/WHEEL
modelgraph-1.0.1.dist-info/top_level.txt
modelgraph-1.0.1.dist-info/RECORD
