Metadata-Version: 2.1
Name: modelgraph
Version: 1.0.1
Summary: Tool for extracting dependency graphs from gotran ODE models
Home-page: https://github.com/ComputationalPhysiology/modelgraph
Author: Henrik Finsberg
Author-email: henriknf@simula.no
License: MIT
Keywords: ODE,models,graphs,dependencies
Platform: UNKNOWN
Classifier: License :: OSI Approved :: MIT License
Classifier: Programming Language :: Python :: 3
Classifier: Programming Language :: Python :: 3 :: Only
Classifier: Programming Language :: Python :: 3.7
Classifier: Programming Language :: Python :: 3.8
Classifier: Programming Language :: Python :: 3.9
Classifier: Programming Language :: Python :: 3.10
Requires-Python: >=3.7
License-File: LICENSE
Requires-Dist: click
Requires-Dist: gotran
Requires-Dist: networkx
Requires-Dist: importlib-metadata ; python_version < "3.8"
Provides-Extra: dev
Requires-Dist: Sphinx ; extra == 'dev'
Requires-Dist: black ; extra == 'dev'
Requires-Dist: build ; extra == 'dev'
Requires-Dist: bump2version ; extra == 'dev'
Requires-Dist: flake8 ; extra == 'dev'
Requires-Dist: ipython ; extra == 'dev'
Requires-Dist: isort ; extra == 'dev'
Requires-Dist: mypy ; extra == 'dev'
Requires-Dist: pdbpp ; extra == 'dev'
Requires-Dist: pip ; extra == 'dev'
Requires-Dist: pre-commit ; extra == 'dev'
Requires-Dist: twine ; extra == 'dev'
Requires-Dist: wheel ; extra == 'dev'
Provides-Extra: docs
Requires-Dist: Sphinx ; extra == 'docs'
Requires-Dist: jupytext ; extra == 'docs'
Requires-Dist: myst-parser ; extra == 'docs'
Requires-Dist: sphinx-press-theme ; extra == 'docs'
Provides-Extra: gui
Requires-Dist: streamlit ; extra == 'gui'
Provides-Extra: plot
Requires-Dist: matplotlib ; extra == 'plot'
Requires-Dist: pydot ; extra == 'plot'
Provides-Extra: test
Requires-Dist: pytest ; extra == 'test'
Requires-Dist: pytest-cov ; extra == 'test'
